samod-0.5.0a3.dist-info/METADATA
samod-0.5.0a3.dist-info/WHEEL
samod/__init__.py
samod/samod.abi3.so
samod-0.5.0a3.dist-info/RECORD
