Metadata-Version: 2.4
Name: samod
Version: 0.5.0a3
Classifier: Development Status :: 3 - Alpha
Classifier: Intended Audience :: Developers
Classifier: License :: OSI Approved :: MIT License
Classifier: Programming Language :: Python :: 3
Classifier: Programming Language :: Python :: 3.8
Classifier: Programming Language :: Python :: 3.9
Classifier: Programming Language :: Python :: 3.10
Classifier: Programming Language :: Python :: 3.11
Classifier: Programming Language :: Python :: 3.12
Classifier: Programming Language :: Rust
Classifier: Programming Language :: Python :: Implementation :: CPython
Classifier: Programming Language :: Python :: Implementation :: PyPy
Classifier: Topic :: Software Development :: Libraries
Summary: Python bindings for samod - Rust implementation of automerge-repo
Keywords: automerge,crdt,sync,collaboration,distributed
Author-email: Alex Good <alex@patternist.xyz>, Kyle Kelley <rgbkrk@gmail.com>
License: MIT
Requires-Python: >=3.8
Project-URL: Homepage, https://github.com/alexjg/samod
Project-URL: Repository, https://github.com/alexjg/samod
Project-URL: Documentation, https://github.com/alexjg/samod/tree/main/samod-py
